{
  "version": 4,
  "lastUserContextId": 7,
  "identities": [
    {
      "userContextId": 6,
      "public": true,
      "icon": "circle",
      "color": "blue",
      "name": "Google"
    },
    {
      "userContextId": 4294967295,
      "public": false,
      "icon": "",
      "color": "",
      "name": "userContextIdInternal.webextStorageLocal",
      "accessKey": ""
    },
    {
      "userContextId": 7,
      "public": true,
      "icon": "briefcase",
      "color": "green",
      "name": "Github"
    }
  ]
}
